aiobmsble/__init__.py
aiobmsble/__main__.py
aiobmsble/basebms.py
aiobmsble/utils.py
aiobmsble/bms/__init__.py
aiobmsble/bms/abc_bms.py
aiobmsble/bms/ant_bms.py
aiobmsble/bms/ant_leg_bms.py
aiobmsble/bms/braunpwr_bms.py
aiobmsble/bms/cbtpwr_bms.py
aiobmsble/bms/cbtpwr_vb_bms.py
aiobmsble/bms/daly_bms.py
aiobmsble/bms/dpwrcore_bms.py
aiobmsble/bms/dummy_bms.py
aiobmsble/bms/ecoworthy_bms.py
aiobmsble/bms/ej_bms.py
aiobmsble/bms/felicity_bms.py
aiobmsble/bms/humsienk_bms.py
aiobmsble/bms/jbd_bms.py
aiobmsble/bms/jikong_bms.py
aiobmsble/bms/lipower_bms.py
aiobmsble/bms/neey_bms.py
aiobmsble/bms/ogt_bms.py
aiobmsble/bms/pace_bms.py
aiobmsble/bms/pro_bms.py
aiobmsble/bms/redodo_bms.py
aiobmsble/bms/renogy_bms.py
aiobmsble/bms/renogy_pro_bms.py
aiobmsble/bms/roypow_bms.py
aiobmsble/bms/seplos_bms.py
aiobmsble/bms/seplos_v2_bms.py
aiobmsble/bms/superb_bms.py
aiobmsble/bms/tdt_bms.py
aiobmsble/bms/tianpwr_bms.py
aiobmsble/bms/topband_bms.py
aiobmsble/bms/vatrer_bms.py
aiobmsble/bms/ws_nova_bms.py
aiobmsble/test_data/__init__.py
aiobmsble/test_data/abc_bms.json
aiobmsble/test_data/ant_bms.json
aiobmsble/test_data/ant_leg_bms.json
aiobmsble/test_data/braunpwr_bms.json
aiobmsble/test_data/cbtpwr_bms.json
aiobmsble/test_data/cbtpwr_vb_bms.json
aiobmsble/test_data/daly_bms.json
aiobmsble/test_data/dpwrcore_bms.json
aiobmsble/test_data/ecoworthy_bms.json
aiobmsble/test_data/ej_bms.json
aiobmsble/test_data/felicity_bms.json
aiobmsble/test_data/humsienk_bms.json
aiobmsble/test_data/ignore.json
aiobmsble/test_data/jbd_bms.json
aiobmsble/test_data/jikong_bms.json
aiobmsble/test_data/lipower_bms.json
aiobmsble/test_data/neey_bms.json
aiobmsble/test_data/ogt_bms.json
aiobmsble/test_data/pace_bms.json
aiobmsble/test_data/pro_bms.json
aiobmsble/test_data/redodo_bms.json
aiobmsble/test_data/renogy_bms.json
aiobmsble/test_data/renogy_pro_bms.json
aiobmsble/test_data/roypow_bms.json
aiobmsble/test_data/seplos_bms.json
aiobmsble/test_data/seplos_v2_bms.json
aiobmsble-0.16.0.dist-info/licenses/LICENSE
aiobmsble-0.16.0.dist-info/METADATA
aiobmsble-0.16.0.dist-info/WHEEL
aiobmsble-0.16.0.dist-info/entry_points.txt
aiobmsble-0.16.0.dist-info/top_level.txt
aiobmsble-0.16.0.dist-info/RECORD
