Metadata-Version: 2.4
Name: aiobmsble
Version: 0.16.0
Summary: Asynchronous Python library to query battery management systems via Bluetooth Low Energy.
Author: @patman15, @daubman, @krahabb
Maintainer: Patrick Loschmidt
License-Expression: Apache-2.0
Project-URL: Homepage, https://github.com/patman15/aiobmsble/
Project-URL: Documentation, https://github.com/patman15/aiobmsble/?tab=readme-ov-file#aiobmsble
Project-URL: Source Code, https://github.com/patman15/aiobmsble/
Project-URL: Bug Reports, https://github.com/patman15/aiobmsble/issues
Keywords: BMS,BLE,battery,Bluetooth
Classifier: Programming Language :: Python :: 3
Classifier: Operating System :: OS Independent
Classifier: Development Status :: 4 - Beta
Classifier: Intended Audience :: Developers
Classifier: Topic :: Software Development :: Libraries :: Python Modules
Requires-Python: >=3.12
License-File: LICENSE
Requires-Dist: bleak>=1.0.1; os_name != "Windows"
Requires-Dist: bleak>=2.0.0; os_name == "Windows"
Requires-Dist: bleak-retry-connector>=4.4.3
Provides-Extra: dev
Requires-Dist: pytest; extra == "dev"
Requires-Dist: pytest-asyncio; extra == "dev"
Requires-Dist: pytest-cov; extra == "dev"
Requires-Dist: pytest-xdist; extra == "dev"
Requires-Dist: hypothesis; extra == "dev"
Requires-Dist: mypy; extra == "dev"
Requires-Dist: ruff<0.15.0,>=0.12.1; extra == "dev"
Requires-Dist: pylint-per-file-ignores; extra == "dev"
Requires-Dist: netaddr; extra == "dev"
Requires-Dist: types-netaddr; extra == "dev"
Requires-Dist: codespell; extra == "dev"
Dynamic: license-file
